<Properties StartupConfiguration="{4C14D780-7D12-4757-8E6E-4F530A82633E}|Default">
  <MonoDevelop.Ide.DebuggingService.PinnedWatches />
  <MultiItemStartupConfigurations />
  <MonoDevelop.Ide.DebuggingService.Breakpoints>
    <BreakpointStore />
  </MonoDevelop.Ide.DebuggingService.Breakpoints>
  <MonoDevelop.Ide.Workbench ActiveDocument="Program.cs">
    <Files>
      <File FileName="Program.cs" Line="310" Column="18" />
      <File FileName="Flights.cs" />
      <File FileName="Customer.cs" />
      <File FileName="Admin.cs" />
    </Files>
    <Pads>
      <Pad Id="ProjectPad">
        <State name="__root__">
          <Node name="Airline-reservation-system" expanded="True" selected="True">
            <Node name="Airline-reservation-system" expanded="True">
              <Node name="Dependencies" expanded="True" />
            </Node>
          </Node>
        </State>
      </Pad>
    </Pads>
  </MonoDevelop.Ide.Workbench>
  <MonoDevelop.Ide.Workspace ActiveConfiguration="Debug" />
  <MonoDevelop.Ide.ItemProperties.Airline-reservation-system PreferredExecutionTarget="MonoDevelop.Default" />
</Properties>